sdbus_async/secrets/__init__.py
sdbus_async/secrets/interfaces.py
sdbus_async/secrets/objects.py
sdbus_async/secrets/py.typed
sdbus_block/secrets/__init__.py
sdbus_block/secrets/interfaces.py
sdbus_block/secrets/objects.py
sdbus_block/secrets/py.typed
sdbus_secrets-0.2.0.dist-info/COPYING
sdbus_secrets-0.2.0.dist-info/COPYING.LESSER
sdbus_secrets-0.2.0.dist-info/METADATA
sdbus_secrets-0.2.0.dist-info/WHEEL
sdbus_secrets-0.2.0.dist-info/top_level.txt
sdbus_secrets-0.2.0.dist-info/RECORD
