Metadata-Version: 2.1
Name: sdbus-secrets
Version: 0.2.0
Summary: Freedesktop secrets binds for sdbus.
Home-page: https://github.com/igo95862/python-sdbus
Author: igo95862
Author-email: igo95862@yandex.ru
License: LGPL-2.1-or-later
Project-URL: Documentation, https://python-sdbus.readthedocs.io/en/latest/
Project-URL: Source, https://github.com/igo95862/python-sdbus/
Project-URL: Tracker, https://github.com/igo95862/python-sdbus/issues/
Keywords: dbus linux freedesktop secrets
Platform: UNKNOWN
Classifier: Development Status :: 4 - Beta
Classifier: Intended Audience :: Developers
Classifier: License :: OSI Approved :: GNU Lesser General Public License v2 or later (LGPLv2+)
Classifier: Operating System :: POSIX :: Linux
Classifier: Programming Language :: Python :: 3 :: Only
Classifier: Topic :: Software Development :: Libraries :: Python Modules
Requires-Python: >=3.7
License-File: COPYING
License-File: COPYING.LESSER
Requires-Dist: sdbus (>=0.8rc2)
